SR2ML/__init__.py
SR2ML/src/ETModel.py
SR2ML/src/FTModel.py
SR2ML/src/GraphModel.py
SR2ML/src/MCSSolver.py
SR2ML/src/MaintenanceModel.py
SR2ML/src/MarginModel.py
SR2ML/src/MarkovModel.py
SR2ML/src/ReliabilityModel.py
SR2ML/src/TDFailureRateReliabilityModel.py
SR2ML/src/__init__.py
SR2ML/src/_utils.py
SR2ML/src/Bases/ModelBase.py
SR2ML/src/Bases/__init__.py
SR2ML/src/MaintenanceModels/Factory.py
SR2ML/src/MaintenanceModels/MaintenanceBase.py
SR2ML/src/MaintenanceModels/PMmodel.py
SR2ML/src/MaintenanceModels/__init__.py
SR2ML/src/MarginModels/Factory.py
SR2ML/src/MarginModels/MarginBase.py
SR2ML/src/MarginModels/PointSetMarginModel.py
SR2ML/src/MarginModels/__init__.py
SR2ML/src/PostProcessors/DataLabeling.py
SR2ML/src/PostProcessors/ETImporter.py
SR2ML/src/PostProcessors/ETStructure.py
SR2ML/src/PostProcessors/FTGate.py
SR2ML/src/PostProcessors/FTImporter.py
SR2ML/src/PostProcessors/FTStructure.py
SR2ML/src/PostProcessors/MCSimporter.py
SR2ML/src/PostProcessors/RiskMeasuresDiscrete.py
SR2ML/src/PostProcessors/__init__.py
SR2ML/src/Reliabilities/BathtubModel.py
SR2ML/src/Reliabilities/ErlangianModel.py
SR2ML/src/Reliabilities/ExponWeibullModel.py
SR2ML/src/Reliabilities/ExponentialModel.py
SR2ML/src/Reliabilities/Factory.py
SR2ML/src/Reliabilities/FatigueLifeModel.py
SR2ML/src/Reliabilities/GammaModel.py
SR2ML/src/Reliabilities/LogLinearModel.py
SR2ML/src/Reliabilities/LognormalModel.py
SR2ML/src/Reliabilities/NormalModel.py
SR2ML/src/Reliabilities/PowerLawModel.py
SR2ML/src/Reliabilities/ReliabilityBase.py
SR2ML/src/Reliabilities/ScipyStatsModelBase.py
SR2ML/src/Reliabilities/WeibullModel.py
SR2ML/src/Reliabilities/__init__.py
sr2ml_ravenframework-0.1rc2.dist-info/METADATA
sr2ml_ravenframework-0.1rc2.dist-info/WHEEL
sr2ml_ravenframework-0.1rc2.dist-info/top_level.txt
sr2ml_ravenframework-0.1rc2.dist-info/RECORD
