Metadata-Version: 2.1
Name: sr2ml-ravenframework
Version: 0.1rc2
Summary: SR2ML plugin for RAVEN framework
Home-page: https://github.com/idaholab/SR2ML
Requires-Python: >=3.9
Requires-Dist: raven-framework >=2.2
